cookiebutter/__init__.py
cookiebutter-0.1.0.dist-info/entry_points.txt
cookiebutter-0.1.0.dist-info/LICENSE
cookiebutter-0.1.0.dist-info/WHEEL
cookiebutter-0.1.0.dist-info/METADATA
cookiebutter-0.1.0.dist-info/RECORD
