Metadata-Version: 2.1
Name: cookiebutter
Version: 0.1.0
Summary: Cookiecutter, but all buttered up 🧈 Use cookiecutter with yaml files, or even with python files
Home-page: https://github.com/tomgrin10/cookiebutter
License: MIT
Keywords: cookiecutter,better,yaml
Author: Tom Gringauz
Author-email: tomgrin10@gmail.com
Requires-Python: >=3.7,<4.0
Classifier: Development Status :: 3 - Alpha
Classifier: Intended Audience :: Developers
Classifier: License :: OSI Approved :: MIT License
Classifier: Programming Language :: Python :: 3
Classifier: Programming Language :: Python :: 3.7
Classifier: Programming Language :: Python :: 3.8
Classifier: Programming Language :: Python :: 3.9
Classifier: Topic :: Utilities
Classifier: Typing :: Typed
Requires-Dist: PyYAML (>=5.3.1,<6.0.0)
Requires-Dist: cookiecutter
Project-URL: Repository, https://github.com/tomgrin10/cookiebutter
